ubuntudesign/documentation_builder/__init__.py
ubuntudesign/documentation_builder/builder.py
ubuntudesign/documentation_builder/cli.py
ubuntudesign/documentation_builder/extensions.py
ubuntudesign/documentation_builder/operations.py
ubuntudesign/documentation_builder/utilities.py
ubuntudesign/documentation_builder/resources/template.html
ubuntudesign.documentation_builder-1.6.0.data/scripts/documentation-builder
ubuntudesign.documentation_builder-1.6.0.dist-info/DESCRIPTION.rst
ubuntudesign.documentation_builder-1.6.0.dist-info/METADATA
ubuntudesign.documentation_builder-1.6.0.dist-info/RECORD
ubuntudesign.documentation_builder-1.6.0.dist-info/WHEEL
ubuntudesign.documentation_builder-1.6.0.dist-info/metadata.json
ubuntudesign.documentation_builder-1.6.0.dist-info/top_level.txt
