Metadata-Version: 2.0
Name: ubuntudesign.documentation-builder
Version: 1.6.0
Summary: A command-line tool for building documentation from repositories into HTML files. Initially based on https://github.com/juju/docs/blob/master/tools/mdbuild.py.
Home-page: https://github.com/ubuntudesign/documentation-builder
Author: Canonical webteam
Author-email: robin+pypi@canonical.com
License: UNKNOWN
Platform: UNKNOWN
Requires-Dist: GitPython (==2.1.9)
Requires-Dist: Jinja2 (==2.8)
Requires-Dist: Markdown (==2.6.6)
Requires-Dist: PyYAML (==3.12)
Requires-Dist: beautifulsoup4 (==4.5.1)
Requires-Dist: markdown-urlize (==0.2.0)
Requires-Dist: mdx-anchors-away (==1.0.1)
Requires-Dist: mdx-foldouts (==1.0.0)
Requires-Dist: pygments (==2.2.0)
Requires-Dist: python-frontmatter (==0.2.1)
